[
    {
        "id": 1,
        "name": "John",
        "loan_details": "GSIS"
    },
    {
        "id": 1,
        "name": "John",
        "loan_details": "GSIS"
    },
    {
        "id": 1,
        "name": "John",
        "loan_details": "GSIS"
    },
    {
        "id": 1,
        "name": "John",
        "loan_details": "GSIS"
    },
    {
        "id": 1,
        "name": "John",
        "loan_details": "GSIS"
    },
    {
        "id": 1,
        "name": "John",
        "loan_details": "GSIS"
    },
    {
        "id": 1,
        "name": "John",
        "loan_details": "GSIS"
    },
    {
        "id": 1,
        "name": "John",
        "loan_details": "GSIS"
    },
    {
        "id": 1,
        "name": "John",
        "loan_details": "GSIS"
    },
    {
        "id": 1,
        "name": "John",
        "loan_details": "GSIS"
    }
]